[
  {
    "title": "欧州株式市場、DAXは2万6000ポイント近く、IBEXは1万9800超えで歴史的記録を達成",
    "summary": "欧州株式市場は上昇基調を継続。地政学的緊張の緩和と米国の堅調な雇用統計が追い風に。",
    "source": [
      "handelsblatt.com",
      "investing.com",
      "bolsamania.com",
      "expansion.com",
      "nasdaq.com"
    ],
    "count": 5
  },
  {
    "title": "ロッキード、ウルトラ・マリタイムの買収に参戦、アルファベットはスペースXに出資、ジャージー・マイクはIPO準備、アップルが市場に反応",
    "summary": "世界の企業活動が加速。防衛、宇宙技術、消費財セクターで大型取引が相次ぐ。一方、ブラックストーンはポートフォリオを収益化し、個人投資家は宇宙・防衛関連に強気の姿勢。",
    "source": [
      "ft.com",
      "nasdaq.com",
      "investing.com",
      "bolsamania.com",
      "/r/stocks"
    ],
    "count": 5
  },
  {
    "title": "スペインがステーブルコイン決済を承認、CNMVが暗号資産規制を更新、欧州でデジタルユーロが進展",
    "summary": "スペイン国立銀行がCrossmintに承認、CNMVは暗号通貨を有価証券規制に組み入れ、ECBはデジタルユーロを推進、英FCAは投資会社の財務書類の不透明性を批判。",
    "source": [
      "expansion.com",
      "bolsamania.com",
      "handelsblatt.com",
      "ft.com",
      "investing.com"
    ],
    "count": 5
  },
  {
    "title": "人工知能の台頭が市場を二分、投資家の楽観論とインフレバブルの懸念",
    "summary": "半導体需要がMicronやAMDを押し上げる一方、アナリストはAIのインフレへの影響を議論。個人投資家は大手ファンドによる操作の可能性を警告。",
    "source": [
      "handelsblatt.com",
      "expansion.com",
      "nasdaq.com",
      "/r/stocks"
    ],
    "count": 4
  },
  {
    "title": "米国の雇用の強さが景気後退懸念を和らげる一方、利益バブルとトランプ氏のFRB批判を巡る議論が過熱",
    "summary": "6月の雇用統計が景気後退懸念を払拭したものの、ウォール街のバリュエーションが過去最高水準にあることや、ドナルド・トランプ氏のFRB批判が投資家の不確実性を高めている。",
    "source": [
      "ft.com",
      "handelsblatt.com",
      "investing.com",
      "/r/stocks"
    ],
    "count": 4
  },
  {
    "title": "アポロとアルディアンが投資先で苦戦、ジュリアス・ベアは最高財務責任者を交代、田辺ファーマが製造子会社を売却",
    "summary": "プライベートエクイティ各社がスーパーマーケットやヘルスケア投資で問題に直面。ジュリアス・ベアは新CFOを任命、田辺ファーマは研究開発に集中するため再編。",
    "source": [
      "ft.com",
      "investing.com",
      "nikkei.com",
      "bolsamania.com"
    ],
    "count": 4
  },
  {
    "title": "スペインのeコマース売上高が1148億ユーロで記録更新、ライアンエアーが仏航空管制を批判、税務当局は93.61億ユーロを還付",
    "summary": "オンライン売上高は前年比20.6%増。アイルランド航空会社はフランスの管制官ストライキによる損失を17億ユーロと試算。スペインの確定申告シーズンは還付額が過去最高に。米国は独立250周年を迎え、富についての考察が広がる。",
    "source": [
      "bolsamania.com",
      "ft.com",
      "handelsblatt.com",
      "expansion.com"
    ],
    "count": 4
  },
  {
    "title": "ラガルドECB総裁、早期退任の可能性に言及、利上げは「正しい」決定と擁護",
    "summary": "欧州中央銀行総裁は引き締め的な金融政策の遺産を支持し、任期前に辞任する可能性を排除せず。",
    "source": [
      "bolsamania.com",
      "handelsblatt.com",
      "expansion.com"
    ],
    "count": 3
  },
  {
    "title": "米国とイランの停戦がホルムズ海峡の交通量を増加、石油・金・ビットコインへの圧力緩和",
    "summary": "停戦により商品市況の見通しが変化。ブレント原油は60ドルまで下落する可能性、金は方向性を模索、ビットコインは6万2000ドルの回復を目指す。",
    "source": [
      "ft.com",
      "handelsblatt.com",
      "expansion.com"
    ],
    "count": 3
  },
  {
    "title": "コロニアルが独不動産市場に参入、エルクロスが上場廃止目的のTOBを提案され、セキュリタイズはナスダックに上場し11%上昇",
    "summary": "スペイン不動産会社（コロニアル）がGenerali Real Estateの51%を取得。CNMVはBondaltiによるエルクロスへのTOBを承認。スペイン初のユニコーン企業（Securitize）がナスダックで上場成功。",
    "source": [
      "bolsamania.com",
      "expansion.com",
      "handelsblatt.com"
    ],
    "count": 3
  },
  {
    "title": "配当とグロース株に資金逃避：Realty Income、Repsol、Comcastなど目標株価を達成した企業",
    "summary": "パッシブ投資とインカム戦略が脚光。強気相場の中、PPG、KMB、PAYXなどの企業がアナリストの平均評価を上回る。",
    "source": [
      "nasdaq.com",
      "expansion.com",
      "handelsblatt.com"
    ],
    "count": 3
  },
  {
    "title": "バークレイズがオートメーション銘柄の割安感を指摘、モーニングスターはフェロビアルをグローバル・フェイバリットに、インサイダー取引が注目",
    "summary": "バークレイズのアナリストがセクター調整後のロボット関連銘柄を推奨。運用会社シルバー・アルファが市場参入。上場企業の役員による売買が投資家の関心を集める。",
    "source": [
      "nasdaq.com",
      "investing.com",
      "expansion.com"
    ],
    "count": 3
  },
  {
    "title": "トランプ氏、FRBへの批判を強め、家族のビジネスを擁護、イランとの緊張緩和の中",
    "summary": "米前大統領がFRBの金融政策を非難し、自身の子供たちの事業活動を正当化。一方、中東の停戦によりエネルギー市場の緊張が緩和。",
    "source": [
      "bolsamania.com",
      "handelsblatt.com",
      "ft.com"
    ],
    "count": 3
  },
  {
    "title": "ステランティスのイタリア生産は13.7%増も株価下落、シーメンスは大幅高、フォードはCATLにバッテリー生産を委託",
    "summary": "自動車セクターの業績はまちまち。ステランティスの生産は増加したが市場は冷たく、シーメンスは値上がり、フォードはバッテリー工場の運営を中国の寧徳時代（CATL）に委託。",
    "source": [
      "investing.com",
      "/r/stocks"
    ],
    "count": 2
  },
  {
    "title": "サンディスク、ウェスタンデジタルからのスピンオフ後6000%以上急騰、投資家は売り時か維持かを議論",
    "summary": "メモリーチップメーカーの株価がその驚異的な上昇と株式分割の可能性で注目を集める。投資フォーラムでは、買われ過ぎかまだ上昇余地があるか議論が交わされている。",
    "source": [
      "nasdaq.com",
      "/r/stocks"
    ],
    "count": 2
  },
  {
    "title": "アジア株が米雇用統計を受けて上昇、日本は税制改革を議論、中国はUnitreeのIPO承認",
    "summary": "日経平均とKospiが上昇。日本は財政赤字と病床削減の影響を評価。中国のロボティクス企業Unitreeが待望の上場承認を取得。",
    "source": [
      "handelsblatt.com",
      "nikkei.com"
    ],
    "count": 2
  },
  {
    "title": "アルセロール・ミッタルとアセリノックスがIbex35の上昇を主導、Rovi、Amadeus、IAGは下落の明暗分かれる展開",
    "summary": "鉄鋼セクターがスペイン株価指数を押し上げる一方、テクノロジー、医薬品、旅行関連銘柄が調整。フェロビアルがモーニングスターに選出され、シルバー・アルファが独立運用会社として始動。",
    "source": [
      "bolsamania.com",
      "expansion.com"
    ],
    "count": 2
  },
  {
    "title": "海外でのリタイア、ナイジェル・ファラージの金ビジネス、米国の富の変化が投資家の関心を集める",
    "summary": "Handelsblattがドイツ国外での退職計画に適したツールを分析。FCAが英国政治家の金地金販売を調査。Financial Timesは米国独立250周年にあたり、富の意味について考察。",
    "source": [
      "handelsblatt.com",
      "ft.com"
    ],
    "count": 2
  },
  {
    "title": "日本、地方選挙や伝統祭り、新たな観光ルートの開設準備、テルモは米国市場に照準",
    "summary": "日本の話題は伝統とビジネスが融合：能登の「あばれ祭り」や黒部峡谷の開通から、群馬の選挙戦、そしてテルモの米国CDMO市場への拡大計画まで。",
    "source": [
      "nikkei.com"
    ],
    "count": 1
  },
  {
    "title": "Euriborが低下、2.7%の節目に接近、スペインの変動金利住宅ローンの負担軽減",
    "summary": "スペインの住宅ローン金利の主要基準指標が低下傾向を続けており、欧州中央銀行による追加利下げ期待と一致している。",
    "source": [
      "expansion.com"
    ],
    "count": 1
  }
]