[
  {
    "title": "Obsidianは『Avowed』の続編を中止し、新しい『Fallout』を開発",
    "summary": "複数の情報筋によると、New Vegasのスタジオがシリーズに復帰する一方、Microsoftは『Avowed 2』のプロジェクトを断念した。",
    "source": [
      "nintendolife.com",
      "pcgamer.com",
      "rockpapershotgun.com",
      "gamespot.com",
      "3djuegos.com",
      "gematsu.com",
      "kotaku.com"
    ],
    "count": 7
  },
  {
    "title": "『Mario Kart Tour』は2025年9月に完全にサービスを終了",
    "summary": "任天堂は、長年のアップデートを経て、モバイル向け無料レースゲームのサービスを終了する。",
    "source": [
      "3djuegos.com",
      "gamesindustry.biz",
      "kotaku.com",
      "gamespot.com",
      "nintendolife.com",
      "gematsu.com",
      "eurogamer.net"
    ],
    "count": 7
  },
  {
    "title": "『Assassin's Creed Black Flag Resynced』が好評とゲームガイドと共に発売",
    "summary": "海賊ゲームの古典のリメイクが好意的なレビューを得て、戦略やロケーションに関する幅広いカバレッジが行われている。",
    "source": [
      "polygon.com",
      "pcgamer.com",
      "eurogamer.net",
      "rockpapershotgun.com",
      "kotaku.com",
      "3djuegos.com"
    ],
    "count": 6
  },
  {
    "title": "MicrosoftがXboxで解雇を続ける中、労働組合や政治家が経営を批判",
    "summary": "複数の報道が、Bethesdaやid Softwareなどのスタジオでの人員削減の影響と、労働組合やバーニー・サンダース上院議員の反応を詳述している。",
    "source": [
      "3djuegos.com",
      "pcgamer.com",
      "kotaku.com",
      "gamespot.com",
      "rockpapershotgun.com",
      "gamesindustry.biz"
    ],
    "count": 6
  },
  {
    "title": "スクウェア・エニックス、モバイルゲーム『Final Fantasy 7 Ever Crisis』を終了",
    "summary": "『ファイナルファンタジー7』をベースにした無料ゲームは、近日中にプレイできなくなり、同社の他のタイトルの撤退に加わる。",
    "source": [
      "pcgamer.com",
      "kotaku.com",
      "3djuegos.com",
      "gamespot.com"
    ],
    "count": 4
  },
  {
    "title": "22万人以上のプレイヤーが、ソニーにPlayStationの物理ディスク廃止中止を求める署名",
    "summary": "コミュニティは、ソリッド・スネークなどの人物の支援を受け、物理フォーマット廃止の可能性に抗議している。",
    "source": [
      "3djuegos.com",
      "gamespot.com",
      "kotaku.com"
    ],
    "count": 3
  },
  {
    "title": "『Destiny 2』ファンが元Bungie CEOにトマトを投げつけるゲームを作成",
    "summary": "コミュニティは、Pete Parsonsの車コレクションを攻撃する「ボスバトル」でスタジオの状況を嘲笑っている。",
    "source": [
      "rockpapershotgun.com",
      "kotaku.com",
      "pcgamer.com"
    ],
    "count": 3
  },
  {
    "title": "Bithell Games、ドラキュラがイングランド王となる没入型シミュレーター『Vampirium 1997』を発表",
    "summary": "『Tron: Catalyst』を手がけたスタジオが、歴史改変物語におけるステルス＆ヴァンパイアゲームを披露。",
    "source": [
      "gamespot.com",
      "eurogamer.net",
      "rockpapershotgun.com"
    ],
    "count": 3
  },
  {
    "title": "MindsEyeの従業員、自社主催のファンイベントに抗議",
    "summary": "スタジオが複数回の解雇を経験する中、労働者は有料イベントに抗議している。",
    "source": [
      "pcgamer.com",
      "gamesindustry.biz",
      "eurogamer.net"
    ],
    "count": 3
  },
  {
    "title": "『ペルソナ4』リバイバルは同性愛嫌悪的な内容を削除、プロデューサーが確認",
    "summary": "古典的なRPGのリメイクは、不快なステレオタイプを排除するためにキャラクターやシーンに変更を加える。",
    "source": [
      "gamespot.com",
      "kotaku.com"
    ],
    "count": 2
  },
  {
    "title": "『Minecraft』、17年を経てついに座る機能を追加",
    "summary": "アップデートにより、キャラクターがさまざまなオブジェクトに座れるようになり、長らく要望の多かった機能が実現。",
    "source": [
      "eurogamer.net",
      "gamespot.com"
    ],
    "count": 2
  },
  {
    "title": "『Palworld』、1.0リリース前にプレイヤー数のマイルストーンを達成、価格は据え置き",
    "summary": "クリーチャーサバイバルゲームは、最終版に向けて準備を進める中、成長を続けている。",
    "source": [
      "eurogamer.net",
      "gamespot.com"
    ],
    "count": 2
  },
  {
    "title": "『Love and Deepspace』の狼男の恋愛対象が永久に消える可能性",
    "summary": "中国政府との論争により、デートゲームで最も人気のあるキャラクターの一人が終焉を迎える。",
    "source": [
      "gamespot.com",
      "kotaku.com"
    ],
    "count": 2
  },
  {
    "title": "元Bungieディレクター、ソニーとの2億ドルの訴訟を和解",
    "summary": "性的不正行為で告発された幹部が合意に達し、『Marathon』のクレジットに登場する。",
    "source": [
      "pcgamer.com",
      "kotaku.com"
    ],
    "count": 2
  },
  {
    "title": "『Fallout』ドラマシリーズがエミー賞10部門にノミネートも、俳優陣は除外",
    "summary": "Prime Videoの実写化は技術部門で評価される一方、主要キャストはノミネートを逃した。",
    "source": [
      "pcgamer.com",
      "gamespot.com"
    ],
    "count": 2
  },
  {
    "title": "『Subnautica 2』、最初の大型アップデートで魚を気絶させる機能を追加",
    "summary": "プレイヤーは最新のメジャーアップデートで、海洋生物を殺さずに身を守ることができるようになった。",
    "source": [
      "eurogamer.net",
      "kotaku.com"
    ],
    "count": 2
  },
  {
    "title": "『The Blood of Dawnwalker』、プロローグ前でもクリア可能",
    "summary": "ヴァンパイアRPGは、開発者が当初想定していたよりも短いプレイ時間で驚かせる。",
    "source": [
      "pcgamer.com",
      "eurogamer.net"
    ],
    "count": 2
  },
  {
    "title": "『GTAトリロジー』リマスターの責任者、長年の沈黙を経てプレイヤーの怒りを理解",
    "summary": "スタジオは発売時の問題を認め、それでも多くのプレイヤーがゲームを楽しんだと述べている。",
    "source": [
      "3djuegos.com",
      "pcgamer.com"
    ],
    "count": 2
  },
  {
    "title": "『Mortal Shell 2』、発売日を8月20日に決定",
    "summary": "待望のソウルライクが、今夏の正式リリースを発表。",
    "source": [
      "3djuegos.com",
      "gematsu.com"
    ],
    "count": 2
  },
  {
    "title": "『Buckshot Roulette』が予告なくXbox Game Passに登場",
    "summary": "散弾銃を使った人気のロシアンルーレットゲームが、Microsoftのサブスクリプションサービスに追加された。",
    "source": [
      "3djuegos.com",
      "gematsu.com"
    ],
    "count": 2
  }
]