[
  {
    "title": "米国とイラン、核開発計画と制裁で歴史的合意",
    "summary": "了解覚書には、イランの石油輸出再開、海上封鎖の終了、3000億ドルの復興計画が盛り込まれている。",
    "source": [
      "Yahoo!ニュース",
      "日経新聞",
      "読売新聞",
      "ニュース速報",
      "朝日新聞"
    ],
    "count": 5
  },
  {
    "title": "G7サミット、重要鉱物・AI・子ども保護で合意し閉幕",
    "summary": "首脳らは重要鉱物の特定国依存を減らし、人工知能を規制することで合意、差異を示しつつ結束を確認した。",
    "source": [
      "NHKニュース",
      "ニュース速報",
      "日経新聞",
      "朝日新聞"
    ],
    "count": 4
  },
  {
    "title": "知床の船長、8人死亡事故で懲役5年の実刑判決",
    "summary": "船長は8人が死亡した難破事故の過失で有罪判決を受け、遺族から強い非難の声が上がっている。",
    "source": [
      "ニュース速報",
      "日経新聞",
      "朝日新聞",
      "NHKニュース"
    ],
    "count": 4
  },
  {
    "title": "与党、食料品消費税を1%に引き下げ実質ゼロを提案",
    "summary": "提案は軽減税率と実質税額を補塡する直接給付を含み、政治的な議論を呼んでいる。",
    "source": [
      "ニュース速報",
      "朝日新聞",
      "日経新聞",
      "NHKニュース"
    ],
    "count": 4
  },
  {
    "title": "バレーボール元日本代表監督、大麻所持で起訴",
    "summary": "佐藤俊一郎・元日本代表選手が練習中に大麻を所持していたとして、麻薬取締法違反で起訴された。",
    "source": [
      "ニュース速報",
      "朝日新聞",
      "読売新聞"
    ],
    "count": 3
  },
  {
    "title": "水泳授業で児童死亡、校長に懲役2年執行猶予判決",
    "summary": "高知地裁は水泳授業中に小学4年生の児童を死亡させたとして校長に過失を認め有罪とした。",
    "source": [
      "朝日新聞",
      "読売新聞"
    ],
    "count": 2
  },
  {
    "title": "母親、16歳息子の死亡で国を提訴　逮捕後不起訴に",
    "summary": "家族は警察の違法捜査が死を招いたと非難、死因は明らかになっていない。",
    "source": [
      "日経新聞",
      "朝日新聞"
    ],
    "count": 2
  },
  {
    "title": "河野洋平元外相が死去、中国への代表団縮小へ",
    "summary": "日本貿易会は河野氏の死去に伴い中国への代表団を縮小、高官会合は予定されていない。",
    "source": [
      "ニュース速報",
      "読売新聞"
    ],
    "count": 2
  },
  {
    "title": "セブン-イレブン、コスト削減で簡易包装おにぎり発売",
    "summary": "同コンビニチェーンはおにぎり包装を簡素化、海苔を省略し色数を減らして包装費を節約する。",
    "source": [
      "読売新聞",
      "日経新聞"
    ],
    "count": 2
  },
  {
    "title": "公正取引委員会、15万社の石油コスト転嫁を緊急調査",
    "summary": "独禁法当局は企業が石油価格上昇分を消費者に転嫁しているかどうかを確認するための緊急調査を行う。",
    "source": [
      "読売新聞",
      "朝日新聞"
    ],
    "count": 2
  },
  {
    "title": "日経平均株価が7万超え、史上最高値を更新",
    "summary": "東京株式市場は3営業日連続で最高値を更新、米国とイランの合意が材料視された。",
    "source": [
      "読売新聞",
      "朝日新聞"
    ],
    "count": 2
  },
  {
    "title": "日本への観光客、2カ月連続減少　中国人客大幅減",
    "summary": "5月の訪日外客数は前年同月を下回り、特に中国人観光客は60%減少した。",
    "source": [
      "朝日新聞",
      "読売新聞"
    ],
    "count": 2
  },
  {
    "title": "プーチン批判のロシア人芸術家、ポーランドで射殺",
    "summary": "ロシア政府に批判的な著名芸術家がポーランドで殺害され、2人が容疑者として拘束された。",
    "source": [
      "朝日新聞",
      "NHKニュース"
    ],
    "count": 2
  },
  {
    "title": "読売ジャイアンツ、小笠原慎之介投手を獲得",
    "summary": "同球団は元中日ドラゴンズでナショナルズ傘下でプレーしていた小笠原投手の獲得を正式発表した。",
    "source": [
      "読売新聞",
      "朝日新聞"
    ],
    "count": 2
  },
  {
    "title": "天皇皇后両陛下がオランダ訪問、戦没者に敬意",
    "summary": "両陛下は国賓訪問中、オランダ兵士の慰霊碑に献花し、現地住民との行事に参加された。",
    "source": [
      "読売新聞",
      "朝日新聞"
    ],
    "count": 2
  },
  {
    "title": "楽天、吉井新監督就任を発表　三木谷オーナーが招聘",
    "summary": "球団は元投手の吉井氏を新監督に選任、三木谷オーナーが『賭け』と表現したオファーを正式受諾した。",
    "source": [
      "Yahoo!ニュース",
      "朝日新聞"
    ],
    "count": 2
  },
  {
    "title": "新幹線個室「Supreme Class」、最大4万2000円で10月導入",
    "summary": "東京～名古屋・大阪間の新幹線に導入される個室は3万2660円から4万2000円の料金設定となる。",
    "source": [
      "ニュース速報",
      "読売新聞"
    ],
    "count": 2
  },
  {
    "title": "最高裁、衆院選は合憲と判断　一票の格差めぐり",
    "summary": "最高裁は投票価値の差が憲法違反だとする訴えを退け、選挙を合憲とした。",
    "source": [
      "NHKニュース",
      "読売新聞"
    ],
    "count": 2
  },
  {
    "title": "野党3党の合併交渉、5カ月経過も停滞",
    "summary": "中道派の小川代表は進展のなさが野党の競争力を制限していると警告した。",
    "source": [
      "ニュース速報",
      "読売新聞"
    ],
    "count": 2
  },
  {
    "title": "投資会社元役員、5000万円着服の疑いで逮捕",
    "summary": "大阪地検は投資会社の元責任者が投資家の資金を私的に流用したとして逮捕した。",
    "source": [
      "日経新聞",
      "朝日新聞"
    ],
    "count": 2
  }
]