[
  {
    "title": "マイクロソフト、Arkaneの閉鎖とBladeのキャンセルを検討、IO InteractiveのRPGへの資金を引き揚げ、解雇の波を引き起こす",
    "summary": "大規模な再編により、Xboxは複数のスタジオやプロジェクトを危機にさらし、IO Interactiveは解雇に見舞われ、小島秀夫は自身のゲームが削減の対象外であることを確認した。",
    "source": [
      "eurogamer.net",
      "gamesindustry.biz",
      "kotaku.com",
      "pcgamer.com",
      "3djuegos.com",
      "rockpapershotgun.com",
      "gematsu.com",
      "gamespot.com",
      "kite.kagi.com"
    ],
    "count": 9
  },
  {
    "title": "ソニー、2028年以降のPlayStationにおける物理ディスクの終了とPS3・PS Vitaストアの閉鎖を確認",
    "summary": "同社はディスク生産の終了とデジタルストアの閉鎖を発表し、ドライブ非搭載のPlayStation 6を予感させ、業界で激しい議論を巻き起こしている。",
    "source": [
      "gamespot.com",
      "kotaku.com",
      "3djuegos.com",
      "eurogamer.net",
      "polygon.com",
      "gematsu.com",
      "nintendolife.com",
      "gamesindustry.biz"
    ],
    "count": 8
  },
  {
    "title": "PlayStation Plus、2026年7月の無料ゲームを公開：Modern Warfare 3と絶賛されたRPG",
    "summary": "ソニーが加入者向けの月間提供を発表。注目タイトルが含まれる一方、ゲーマーコミュニティでは賛否両論の反応を引き起こしている。",
    "source": [
      "3djuegos.com",
      "polygon.com",
      "gamespot.com",
      "gematsu.com",
      "kotaku.com"
    ],
    "count": 5
  },
  {
    "title": "マリオカート ワールド、新コース「ノックアウトツアー」とフォトモードを含む大型アップデート1.7.0を配信",
    "summary": "任天堂が待望のパッチをリリース。未公開のルートを追加し、レースゲームにおける長いコンテンツ不足を打破した。",
    "source": [
      "eurogamer.net",
      "gamespot.com",
      "gematsu.com",
      "kite.kagi.com",
      "nintendolife.com"
    ],
    "count": 5
  },
  {
    "title": "Rockstarが強制クランチを課していると非難、従業員はGTA 6に向けて労働組合の承認を求める",
    "summary": "内部報告により、強制的な残業文化と男女間の賃金格差が明らかになり、スタジオは英国政府の介入の可能性に直面している。",
    "source": [
      "rockpapershotgun.com",
      "eurogamer.net",
      "gamesindustry.biz",
      "3djuegos.com",
      "gamespot.com"
    ],
    "count": 5
  },
  {
    "title": "Subnautica 2の法廷闘争が終結：スタジオはボーナスを受け取り、Unknown WorldsのCEOが辞任",
    "summary": "Kraftonと開発者の間の長い法的紛争の末、約束されたボーナスの支払いとTed Gillの完全な退社が確認された。",
    "source": [
      "eurogamer.net",
      "polygon.com",
      "gamespot.com",
      "kotaku.com"
    ],
    "count": 4
  },
  {
    "title": "Steam Machineへの関心が再燃、新たなクローン、カスタムアクセサリー、技術分析が登場",
    "summary": "フランスの小売業者が低価格クローンを発売、Dbrandは非公式のPortal筐体をキャンセル、コミュニティはValveのオープンコンソールコンセプトの復活を祝う。",
    "source": [
      "pcgamer.com",
      "kite.kagi.com",
      "rockpapershotgun.com",
      "kotaku.com"
    ],
    "count": 4
  },
  {
    "title": "Half-Life 2のアートディレクターの遺作『Guns of Eschaton』、西部劇のソウルライクとして発表",
    "summary": "2025年に死去したViktor Antonovの遺作は、西部開拓時代を舞台にソウルライクなメカニクスを備えたユニークなFPS体験を約束する。",
    "source": [
      "kite.kagi.com",
      "rockpapershotgun.com",
      "pcgamer.com"
    ],
    "count": 3
  },
  {
    "title": "『リズムヘブン グルーヴ』の批評家たちは、本作を必須タイトルであり、Nintendo Switchにふさわしい最高の締めくくりだと絶賛",
    "summary": "音楽シリーズの最新作は、その創造性とユニークなデザインで賞賛を集め、現行コンソール世代への完璧な別れとなる。",
    "source": [
      "nintendolife.com",
      "eurogamer.net",
      "3djuegos.com"
    ],
    "count": 3
  },
  {
    "title": "「Stop Killing Games」運動が痛恨の敗北、ESAはプライベートサーバーに関する物議を醸す見解を修正",
    "summary": "業界を代表する団体はコミュニティサーバーは違法ではないと釈明するが、批判を鎮めたり市民運動の法的後退を覆したりすることはできなかった。",
    "source": [
      "pcgamer.com",
      "gamespot.com",
      "3djuegos.com"
    ],
    "count": 3
  },
  {
    "title": "EA、1ヶ月足らずの間に2度、Battlefield 6の経験値ブースターを誤って適用および削除",
    "summary": "開発元は、自ら誤って実装した進行システムの変更を元に戻し、プレイヤーの間に混乱を引き起こしている。",
    "source": [
      "pcgamer.com",
      "eurogamer.net"
    ],
    "count": 2
  },
  {
    "title": "Helldivers 2、ドナルド・トランプの政策を明確に風刺した『壁を築く』キャンペーンを開始",
    "summary": "新アップデート「Frontlines of Freedom」は、ゲームのフィクションと現実世界の政治を融合させた「銀河系を再び安全に」するキャンペーンを導入する。",
    "source": [
      "rockpapershotgun.com",
      "gamespot.com"
    ],
    "count": 2
  },
  {
    "title": "Godotエンジン、AI生成コードの寄稿を禁止、明示的な申告を義務化",
    "summary": "Slay the Spire 2などのタイトルで使用されている人気ゲームエンジンの開発者は、「バイブコーディング」やAIの悪質な行為に対して断固たる姿勢を取っている。",
    "source": [
      "rockpapershotgun.com",
      "pcgamer.com"
    ],
    "count": 2
  },
  {
    "title": "『トゥームレイダー ディフィニティブエディション』、Limited Run GamesよりNintendo Switch 2向けパッケージ版発売決定",
    "summary": "PlayStationでのディスク終了の議論の真っ只中、ララ・クロフトのアドベンチャーコレクションが任天堂の新コンソールでのパッケージ版を発表。",
    "source": [
      "eurogamer.net",
      "nintendolife.com"
    ],
    "count": 2
  },
  {
    "title": "『Love and Deepspace』、プレイヤーコミュニティの強い抗議を受け新恋愛対象キャラ「ヴァルコ」を中止",
    "summary": "キャラクター発表後、ファンからの大規模かつ否定的な反応により、スタジオはゲームへの導入を撤回せざるを得なくなった。",
    "source": [
      "gamespot.com",
      "kite.kagi.com"
    ],
    "count": 2
  },
  {
    "title": "Baldur's Gateのオリジナルデザイナー、Larian Studiosの成功との競争を恐れ第4作の指揮を拒否",
    "summary": "BioWareのベテランであるJames Ohlenは、Baldur's Gate 3の影響力があまりにも大きく、そのクオリティに対抗するのは不可能だと考えていると説明している。",
    "source": [
      "kotaku.com",
      "3djuegos.com"
    ],
    "count": 2
  },
  {
    "title": "期待のポストアポカリプスシューター『Cinder City』、市場危機の中での非常に高いRAM要件で物議",
    "summary": "このオープンワールドのインディーゲームは『The Division』と比較され、価格高騰とAI需要の中で最大64GBのメモリを要求するとして批判されている。",
    "source": [
      "pcgamer.com",
      "3djuegos.com"
    ],
    "count": 2
  },
  {
    "title": "元PlayStation責任者のShawn Layden、ソニーの新戦略（PCへの同時リリースを行わないこと）を批判",
    "summary": "元幹部は、PCへの同時リリースを撤回するのは間違いであり、現在の会社の方針に反すると考えている。",
    "source": [
      "pcgamer.com",
      "3djuegos.com"
    ],
    "count": 2
  },
  {
    "title": "GameStop、ポケモン30周年記念商品に法外な値上げを実施",
    "summary": "この小売チェーンは、任天堂フランチャイズの記念商品の法外な価格についてソーシャルメディアで強く批判されている。",
    "source": [
      "polygon.com"
    ],
    "count": 1
  },
  {
    "title": "新たな集団訴訟、RAMメーカーが人為的に価格を吊り上げる独占を形成したと告発",
    "summary": "メモリ市場全体に影響を及ぼすこの訴訟は、長年にわたりDRAMとNANDのコストを膨らませ、消費者や企業に影響を与えたとされるカルテルの存在を指摘している。",
    "source": [
      "gamespot.com"
    ],
    "count": 1
  }
]