[
  {
    "title": "Microsoft sube los precios de las consolas Xbox Series hasta 150 dólares en agosto",
    "summary": "El aumento, atribuido a la crisis de componentes y al alza de costes, afecta a todos los modelos y elimina la versión de 2 TB.",
    "source": [
      "geeknetic.es",
      "hardzone.es",
      "tomshardware.com",
      "techpowerup.com",
      "videocardz.com",
      "/r/hardware"
    ],
    "count": 6
  },
  {
    "title": "Apple incrementa los precios de sus dispositivos por la subida de la memoria RAM",
    "summary": "La compañía aplica aumentos en Mac, iPad y otros productos debido al encarecimiento de los chips NAND Flash y DRAM.",
    "source": [
      "techpowerup.com",
      "geeknetic.es",
      "tomshardware.com",
      "hardzone.es"
    ],
    "count": 4
  },
  {
    "title": "Surgen alternativas a la Steam Machine para competir con su elevado precio",
    "summary": "Un minorista francés presenta un PC burlón llamado 'Stim Machine' y aparecen proyectos DIY fabricados con impresora 3D.",
    "source": [
      "/r/hardware",
      "techpowerup.com",
      "profesionalreview.com"
    ],
    "count": 3
  },
  {
    "title": "IBM revela una tecnología de transistores sub-1 nanómetro para futuros chips",
    "summary": "El nuevo método de apilamiento vertical permite seguir avanzando en la miniaturización de los procesadores.",
    "source": [
      "/r/hardware",
      "profesionalreview.com",
      "techpowerup.com"
    ],
    "count": 3
  },
  {
    "title": "Tim Sweeney critica a Valve por etiquetar juegos con IA generativa",
    "summary": "El CEO de Epic Games tacha de 'irresponsable' la decisión de Steam de incluir etiquetas sobre contenido generado por IA.",
    "source": [
      "geeknetic.es",
      "techpowerup.com",
      "tomshardware.com"
    ],
    "count": 3
  },
  {
    "title": "Valve reduce sus promesas de rendimiento para la Steam Machine",
    "summary": "La compañía cambia la afirmación de 4K a 60 FPS por un más vago 'hasta 4K'.",
    "source": [
      "techpowerup.com",
      "videocardz.com"
    ],
    "count": 2
  },
  {
    "title": "AMD relanza el Ryzen 7 5800X3D en una edición especial 10.º aniversario",
    "summary": "El procesador vuelve al mercado con existencias limitadas que ya están siendo acaparadas por revendedores.",
    "source": [
      "videocardz.com",
      "tomshardware.com"
    ],
    "count": 2
  },
  {
    "title": "ASUS devuelve el cifrado TSME a sus placas AM5 con una BIOS beta",
    "summary": "La compañía responde a la controversia y restaura la seguridad en sus placas base para procesadores Ryzen 9000.",
    "source": [
      "geeknetic.es",
      "tomshardware.com"
    ],
    "count": 2
  },
  {
    "title": "AceMagic lanza una promoción con hasta un 20% de descuento en sus mini PC",
    "summary": "Los equipos con AMD Ryzen están disponibles a precios reducidos mediante cupón exclusivo por tiempo limitado.",
    "source": [
      "techpowerup.com",
      "profesionalreview.com"
    ],
    "count": 2
  },
  {
    "title": "GTA VI: rumores de censura y posible lanzamiento en disco para diciembre",
    "summary": "Circulan informaciones contradictorias sobre el contenido del juego y su formato físico.",
    "source": [
      "profesionalreview.com",
      "videocardz.com"
    ],
    "count": 2
  },
  {
    "title": "Windows 10 amplía su soporte gratuito hasta 2027",
    "summary": "Los usuarios podrán seguir actualizando el sistema operativo sin coste adicional durante tres años más.",
    "source": [
      "hardzone.es"
    ],
    "count": 1
  },
  {
    "title": "Sony confirma despidos masivos en Bungie",
    "summary": "El estudio de videojuegos sufre un importante recorte de personal como parte de la reestructuración de Sony.",
    "source": [
      "techpowerup.com"
    ],
    "count": 1
  },
  {
    "title": "Riot elimina el requisito de ejecución permanente de su anticheat Vanguard",
    "summary": "El nuevo modo bajo demanda exige una estricta configuración de seguridad en Windows 11.",
    "source": [
      "tomshardware.com"
    ],
    "count": 1
  },
  {
    "title": "El auge de los tokens de IA se desinfla por los altos costes",
    "summary": "Una filtración de audio de una consultora revela que nadie sabe cómo medir la efectividad de la IA.",
    "source": [
      "tomshardware.com"
    ],
    "count": 1
  },
  {
    "title": "Apple saltaría los chips M6 Pro y M6 Max para pasar directamente al M7",
    "summary": "Los próximos procesadores de Apple podrían omitir una generación según informes de la cadena de suministro.",
    "source": [
      "videocardz.com"
    ],
    "count": 1
  },
  {
    "title": "Morgan Stanley pronostica que AMD EPYC Venice superará en volumen a las CPU NVIDIA Vera en 2027",
    "summary": "Los analistas auguran un crecimiento significativo de los procesadores EPYC frente a las propuestas de NVIDIA.",
    "source": [
      "profesionalreview.com"
    ],
    "count": 1
  },
  {
    "title": "El Intel Core Ultra 9 285K baja a 445 dólares en Amazon",
    "summary": "El procesador tope de gama de Intel reduce su precio significativamente en la plataforma de ventas.",
    "source": [
      "videocardz.com"
    ],
    "count": 1
  },
  {
    "title": "Framework adopta los SSD ADATA XPG MARS 970 y advierte de próximas subidas de precio en CPU",
    "summary": "La compañía de portátiles modulares actualiza sus componentes y alerta sobre aumentos futuros.",
    "source": [
      "techpowerup.com"
    ],
    "count": 1
  },
  {
    "title": "Enshrouded anuncia su lanzamiento completo y fecha para PS5 tras dos años en acceso anticipado",
    "summary": "El juego de supervivencia y acción sale de Early Access con una versión 1.0 en todas las plataformas.",
    "source": [
      "techpowerup.com"
    ],
    "count": 1
  },
  {
    "title": "Half-Life 2 ya se puede jugar en el navegador gracias a una versión no oficial en WebGL 2",
    "summary": "Un proyecto de la comunidad permite disfrutar del clásico de Valve sin necesidad de descargar nada.",
    "source": [
      "videocardz.com"
    ],
    "count": 1
  }
]